get_summary/createsummary.py
get_summary-0.0.0.3.dist-info/LICENSE
get_summary-0.0.0.3.dist-info/METADATA
get_summary-0.0.0.3.dist-info/WHEEL
get_summary-0.0.0.3.dist-info/top_level.txt
get_summary-0.0.0.3.dist-info/RECORD
