Metadata-Version: 2.1
Name: get-summary
Version: 0.0.0.3
Summary: A Python package which will helps you to get summary report of any webpage content or summary of paragraphs
Home-page: https://github.com/Vijayraj72/get-summary
Author: vijay saw
Author-email: imvijayraj72@gmail.com
License: MIT
Keywords: summary,content summary,website summary,get summary,article summary,get article summary
Platform: UNKNOWN
Classifier: License :: OSI Approved :: MIT License
Classifier: Programming Language :: Python :: 3
Classifier: Programming Language :: Python :: 3.7
Requires-Dist: nltk
